[{"startTime": "01:00 ", "endTime": " 02:00", "productImage": "https://imagessl.hyundaihmall.com/static/2/8/10/79/2079108271_0_140.jpg", "productName": "LG \uc6b8\ud2b8\ub77cHD TV 65\ud615(163cm) 65UK6800HNC", "customerPrice": "1,690,000\uc6d0", "productCategory": "\ub514\uc9c0\ud138\uac00\uc804", "marketPrice": "1,930,000\uc6d0", "benefitList": ["12%"], "productLink": "https://www.hyundaihmall.com/front/pda/itemPtc.do?slitmCd=2079108271"}, {"startTime": "01:00 ", "endTime": " 02:00", "productImage": "https://imagessl.hyundaihmall.com/static/7/7/10/79/2079107734_0_140.jpg", "productName": "LG \uc6b8\ud2b8\ub77cHD TV 55\ud615(138cm) 55UK6800HNC", "customerPrice": "1,290,000\uc6d0", "productCategory": "\ub514\uc9c0\ud138\uac00\uc804", "marketPrice": "1,430,000\uc6d0", "benefitList": ["10%"], "productLink": "https://www.hyundaihmall.com/front/pda/itemPtc.do?slitmCd=2079107734"}, {"startTime": "01:00 ", "endTime": " 02:00", "productImage": "https://imagessl.hyundaihmall.com/static/1/2/11/79/2079112105_0_140.JPG", "productName": "LG \uc6b8\ud2b8\ub77cHD TV 75\ud615(189cm) 75UK6200KNB", "customerPrice": "2,790,000\uc6d0", "productCategory": "\ub514\uc9c0\ud138\uac00\uc804", "marketPrice": "3,090,000\uc6d0", "benefitList": ["10%"], "productLink": "https://www.hyundaihmall.com/front/pda/itemPtc.do?slitmCd=2079112105"}, {"startTime": "02:00 ", "endTime": " 06:00", "productImage": "https://imagessl.hyundaihmall.com/static/6/0/58/78/2078580659_0_140.jpg", "productName": "\ub808\ub525\ud37c\ud4f8 \ud5a5\uc218 \ucd5c\ub2e4\uc6a9\ub7c9 \ud328\ud0a4\uc9c0", "customerPrice": "89,000\uc6d0", "productCategory": "\ub2e4\uc2dc\ubcf4\ub294 \uc778\uae30\uc0c1\ud488(\uc7ac)(ZONE a.m.)", "marketPrice": 0, "benefitList": [], "productLink": "https://www.hyundaihmall.com/front/pda/itemPtc.do?slitmCd=2078580659"}, {"startTime": "02:00 ", "endTime": " 06:00", "productImage": "https://imagessl.hyundaihmall.com/static/5/9/78/77/2077789558_0_140.jpg", "productName": "\ud14c\uc774\ud2b8 \ub0a8\uc131 \ucf54\ud2bc\ubaa8\ub2ec\ubc18\ud314\uc154\uce20 5\uc885", "customerPrice": "69,900\uc6d0", "productCategory": "\ub2e4\uc2dc\ubcf4\ub294 \uc778\uae30\uc0c1\ud488(\uc7ac)(ZONE a.m.)", "marketPrice": 0, "benefitList": [], "productLink": "https://www.hyundaihmall.com/front/pda/itemPtc.do?slitmCd=2077789558"}, {"startTime": "06:00 ", "endTime": " 07:15", "productImage": "https://imagessl.hyundaihmall.com/static/6/2/14/76/2076142670_0_140.jpg", "productName": "[Hmall][\uc140\ub809\uc2a4]\ub9e4\uc77c\uc720\uc5c5 \ub9e4\uc77c\ucf54\uc5b4\ud504\ub85c\ud2f4 288g*9\uce94 + \uace0\ub2e8\ubc31\uba40\ud2f0\ube44\ud0c0\ubbfc125ml*14\ud3ec", "customerPrice": "197,000\uc6d0", "productCategory": "\uc2dd\ud488", "marketPrice": "198,000\uc6d0", "benefitList": ["1%"], "productLink": "https://www.hyundaihmall.com/front/pda/itemPtc.do?slitmCd=2076142670"}, {"startTime": "06:00 ", "endTime": " 07:15", "productImage": "https://imagessl.hyundaihmall.com/static/3/1/42/76/2076421340_0_140.jpg", "productName": "[\uc140\ub809\uc2a4]\ub9e4\uc77c\uc720\uc5c5 \ub9e4\uc77c\ucf54\uc5b4\ud504\ub85c\ud2f4 288g*9\uce94 + \uace0\ub2e8\ubc31\uba40\ud2f0\ube44\ud0c0\ubbfc125ml*14\ud3ec", "customerPrice": "197,000\uc6d0", "productCategory": "\uc2dd\ud488", "marketPrice": "198,000\uc6d0", "benefitList": ["1%"], "productLink": "https://www.hyundaihmall.com/front/pda/itemPtc.do?slitmCd=2076421340"}, {"startTime": "06:00 ", "endTime": " 07:15", "productImage": "https://imagessl.hyundaihmall.com/static/8/2/14/76/2076142879_0_140.jpg", "productName": "[\ub2e8\ud488]\ub9e4\uc77c\uc720\uc5c5 \ub9e4\uc77c\ucf54\uc5b4\ud504\ub85c\ud2f4 288g*1\uce94", "customerPrice": "29,000\uc6d0", "productCategory": "\uc2dd\ud488", "marketPrice": 0, "benefitList": [], "productLink": "https://www.hyundaihmall.com/front/pda/itemPtc.do?slitmCd=2076142879"}, {"startTime": "07:15 ", "endTime": " 09:25", "productImage": "https://imagessl.hyundaihmall.com/static/4/0/11/79/2079110496_0_140.jpg", "productName": "19 Summer \uc5d0\uc774\uc564\ub514 USA \ucf54\ud2bc \ubaa8\ub2ec \ub808\ud130\ub9c1 \ud2f0\uc154\uce20 5\uc885", "customerPrice": "66,410\uc6d0", "productCategory": "\uc2a4\ud0c0\uc77c\ud37c\uc2a4\ud2b8", "marketPrice": "69,900\uc6d0", "benefitList": ["5%"], "productLink": "https://www.hyundaihmall.com/front/pda/itemPtc.do?slitmCd=2079110496"}, {"startTime": "07:15 ", "endTime": " 09:25", "productImage": "https://imagessl.hyundaihmall.com/static/5/0/11/79/2079110520_0_140.jpg", "productName": "[Hmall] \uc5d0\uc774\uc564\ub514 USA \ucf54\ud2bc \ubaa8\ub2ec \ub808\ud130\ub9c1 \ud2f0\uc154\uce20 5\uc885", "customerPrice": "66,410\uc6d0", "productCategory": "\uc2a4\ud0c0\uc77c\ud37c\uc2a4\ud2b8", "marketPrice": "69,900\uc6d0", "benefitList": ["5%"], "productLink": "https://www.hyundaihmall.com/front/pda/itemPtc.do?slitmCd=2079110520"}, {"startTime": "09:25 ", "endTime": " 11:40", "productImage": "https://imagessl.hyundaihmall.com/static/0/5/32/79/2079325034_0_140.jpg", "productName": "\ub354\uc2a4\ud150 \uba54\ud0c8\uadf8\ub77c\uc6b4\ub4dc \uc2a4\ud150\uc6a9\uae30 \ud480\uc138\ud2b8", "customerPrice": "169,200\uc6d0", "productCategory": "\ub178\uc591\uc120\uacfc \uac00\uce58\uc1fc\ud551", "marketPrice": "199,000\uc6d0", "benefitList": ["15%"], "productLink": "https://www.hyundaihmall.com/front/pda/itemPtc.do?slitmCd=2079325034"}, {"startTime": "09:25 ", "endTime": " 11:40", "productImage": "https://imagessl.hyundaihmall.com/static/1/5/32/79/2079325121_0_140.jpg", "productName": "\ub354\uc2a4\ud150 \uba54\ud0c8\uadf8\ub77c\uc6b4\ub4dc \uc2a4\ud150\uc6a9\uae30 1\uc138\ud2b8", "customerPrice": "129,000\uc6d0", "productCategory": "\ub178\uc591\uc120\uacfc \uac00\uce58\uc1fc\ud551", "marketPrice": 0, "benefitList": [], "productLink": "https://www.hyundaihmall.com/front/pda/itemPtc.do?slitmCd=2079325121"}, {"startTime": "09:25 ", "endTime": " 11:40", "productImage": "https://imagessl.hyundaihmall.com/static/1/6/23/77/2077236147_0_140.jpg", "productName": "[\ub85c\uc988\uace8\ub4dc 19+6] \uc0bc\uc131 \ubb34\ud48d\ud074\ub798\uc2dd \uc5d0\uc5b4\ucee8 \ud648\uba40\ud2f0\ud615 [AF19R7970RFR] (\uc0ac\uc740\ud488 : \uc0bc\uc131 \uacf5\uae30\uccad\uc815\uae30)", "customerPrice": "3,047,590\uc6d0", "productCategory": "\ub178\uc591\uc120\uacfc \uac00\uce58\uc1fc\ud551", "marketPrice": "3,499,000\uc6d0", "benefitList": ["13%"], "productLink": "https://www.hyundaihmall.com/front/pda/itemPtc.do?slitmCd=2077236147"}, {"startTime": "09:25 ", "endTime": " 11:40", "productImage": "https://imagessl.hyundaihmall.com/static/2/7/18/79/2079187281_0_140.PNG", "productName": "[\ud654\uc774\ud2b8 19+6] \uc0bc\uc131 \ubb34\ud48d\uc5d0\uc5b4\ucee8 \ud648\uba40\ud2f0\ud615 [AF19R7573WSR] (\uc0ac\uc740\ud488 : \uc0bc\uc131 \uacf5\uae30\uccad\uc815\uae30+\uc0bc\uc131 \uc120\ud48d\uae30)", "customerPrice": "2,849,000\uc6d0", "productCategory": "\ub178\uc591\uc120\uacfc \uac00\uce58\uc1fc\ud551", "marketPrice": "2,949,000\uc6d0", "benefitList": ["3%"], "productLink": "https://www.hyundaihmall.com/front/pda/itemPtc.do?slitmCd=2079187281"}, {"startTime": "09:25 ", "endTime": " 11:40", "productImage": "https://imagessl.hyundaihmall.com/static/2/4/19/79/2079194290_0_140.PNG", "productName": "[\ud654\uc774\ud2b8 16+6] \uc0bc\uc131 \ubb34\ud48d\uc2ac\ub9bc\uc5d0\uc5b4\ucee8 \ud648\uba40\ud2f0\ud615 [AF16R5773WSR] (\uc0ac\uc740\ud488 : \uac00\uc804 4\uc885)", "customerPrice": "2,299,000\uc6d0", "productCategory": "\ub178\uc591\uc120\uacfc \uac00\uce58\uc1fc\ud551", "marketPrice": "2,399,000\uc6d0", "benefitList": ["4%"], "productLink": "https://www.hyundaihmall.com/front/pda/itemPtc.do?slitmCd=2079194290"}, {"startTime": "09:25 ", "endTime": " 11:40", "productImage": "https://imagessl.hyundaihmall.com/static/3/7/18/79/2079187350_0_140.png", "productName": "[\ud654\uc774\ud2b8 19] \uc0bc\uc131 \ubb34\ud48d\uc5d0\uc5b4\ucee8 \uc2a4\ud0e0\ub4dc\ud615 [AF19R7573WSK] (\uc0ac\uc740\ud488 : \uc0bc\uc131 \uacf5\uae30\uccad\uc815\uae30+\uc0bc\uc131 \uc120\ud48d\uae30)", "customerPrice": "2,449,000\uc6d0", "productCategory": "\ub178\uc591\uc120\uacfc \uac00\uce58\uc1fc\ud551", "marketPrice": "2,549,000\uc6d0", "benefitList": ["4%"], "productLink": "https://www.hyundaihmall.com/front/pda/itemPtc.do?slitmCd=2079187350"}, {"startTime": "09:25 ", "endTime": " 11:40", "productImage": "https://imagessl.hyundaihmall.com/static/6/4/19/79/2079194654_0_140.png", "productName": "[\ud654\uc774\ud2b8 16] \uc0bc\uc131 \ubb34\ud48d\uc2ac\ub9bc\uc5d0\uc5b4\ucee8 \uc2a4\ud0e0\ub4dc\ud615 [AF16R5773WSK] (\uc0ac\uc740\ud488 : \uac00\uc804 4\uc885)", "customerPrice": "1,899,000\uc6d0", "productCategory": "\ub178\uc591\uc120\uacfc \uac00\uce58\uc1fc\ud551", "marketPrice": "1,999,000\uc6d0", "benefitList": ["5%"], "productLink": "https://www.hyundaihmall.com/front/pda/itemPtc.do?slitmCd=2079194654"}, {"startTime": "11:40 ", "endTime": " 12:40", "productImage": "https://imagessl.hyundaihmall.com/static/1/0/07/73/2073070142_0_140.jpg", "productName": "[\ub80c\ud0c8]\ucfe0\ucfe0 \uc815\uc218\uae30", "customerPrice": 0, "productCategory": "\ub80c\ud0c8", "marketPrice": 0, "benefitList": [], "productLink": "https://www.hyundaihmall.com/front/pda/itemPtc.do?slitmCd=2073070142"}, {"startTime": "12:40 ", "endTime": " 13:40", "productImage": "https://imagessl.hyundaihmall.com/static/2/8/01/72/2072018225_0_140.jpg", "productName": "\ub9e5\ud3ec\uba38\uc2a4 \ub9e4\uc9c1 \uc6d4\ub4dc \uc138\ud2b8 [\ucf54\ub529 \ud328\ud0a4\uc9c0]", "customerPrice": "353,000\uc6d0", "productCategory": "\uc544\ub3d9\ub808\ud3ec\uce20", "marketPrice": "369,000\uc6d0", "benefitList": ["4%"], "productLink": "https://www.hyundaihmall.com/front/pda/itemPtc.do?slitmCd=2072018225"}, {"startTime": "13:40 ", "endTime": " 14:40", "productImage": "https://imagessl.hyundaihmall.com/static/4/0/52/74/2074520437_0_140.jpg", "productName": "\ub374\ub9c8\ud06c \uc720\uc0b0\uade0 \uc774\uc57c\uae30 \uc2dc\uc98c3", "customerPrice": "178,200\uc6d0", "productCategory": "\uc2dd\ud488", "marketPrice": "198,000\uc6d0", "benefitList": ["10%"], "productLink": "https://www.hyundaihmall.com/front/pda/itemPtc.do?slitmCd=2074520437"}, {"startTime": "13:40 ", "endTime": " 14:40", "productImage": "https://imagessl.hyundaihmall.com/static/7/8/43/76/2076438761_0_140.jpg", "productName": "\ub374\ub9c8\ud06c \uc720\uc0b0\uade0 \uc774\uc57c\uae30 \uc2dc\uc98c3 1\ubc15\uc2a4", "customerPrice": "92,000\uc6d0", "productCategory": "\uc2dd\ud488", "marketPrice": 0, "benefitList": [], "productLink": "https://www.hyundaihmall.com/front/pda/itemPtc.do?slitmCd=2076438761"}, {"startTime": "14:40 ", "endTime": " 15:40", "productImage": "https://imagessl.hyundaihmall.com/static/3/2/93/78/2078932314_0_140.jpg", "productName": "(\ubb34)THE\ub4e0\ub4e0\ud55c \uac04\ubcd1\ube44 \uce58\ub9e4\ubcf4\ud5d8", "customerPrice": "080-000-0000", "productCategory": "\uae08\uc735\uc0c1\ud488", "marketPrice": 0, "benefitList": [], "productLink": "https://www.hyundaihmall.com/front/pda/itemPtc.do?slitmCd=2078932314"}, {"startTime": "15:40 ", "endTime": " 16:40", "productImage": "https://imagessl.hyundaihmall.com/static/4/1/06/79/2079061429_0_140.jpg", "productName": "\ucc38\uc874 \ub514\uc5d0\uc774\uc9c0 \ube14\ub799 \uc5d0\ub514\uc158 \uc5b4\ubc84\uc774\ub0a0 \ud2b9\uc9d1 \uad6c\uc131 \ud480 \uae30\ucd08 \uc138\ud2b8", "customerPrice": "79,000\uc6d0", "productCategory": "\ubdf0\ud2f0", "marketPrice": "80,000\uc6d0", "benefitList": ["1%"], "productLink": "https://www.hyundaihmall.com/front/pda/itemPtc.do?slitmCd=2079061429"}, {"startTime": "15:40 ", "endTime": " 16:40", "productImage": "https://imagessl.hyundaihmall.com/static/7/8/43/47/2047438792_0_140.jpg", "productName": "\ucc38\uc874 \ube14\ub799\uc5d0\ub514\uc158 \ud480 \uae30\ucd08 \uad00\ub9ac \ub354\ube14\uad6c\uc131", "customerPrice": "80,000\uc6d0", "productCategory": "\ubdf0\ud2f0", "marketPrice": 0, "benefitList": [], "productLink": "https://www.hyundaihmall.com/front/pda/itemPtc.do?slitmCd=2047438792"}, {"startTime": "15:40 ", "endTime": " 16:40", "productImage": "https://imagessl.hyundaihmall.com/static/8/5/11/71/2071115820_0_140.jpg", "productName": "\ucc38\uc874 \uae30\ucd08 \ubcf8\ud488 \ud2b8\ub9ac\ud50c\uad6c\uc131", "customerPrice": "79,000\uc6d0", "productCategory": "\ubdf0\ud2f0", "marketPrice": "80,000\uc6d0", "benefitList": ["1%"], "productLink": "https://www.hyundaihmall.com/front/pda/itemPtc.do?slitmCd=2071115820"}, {"startTime": "15:40 ", "endTime": " 16:40", "productImage": "https://imagessl.hyundaihmall.com/static/9/2/79/75/2075792903_0_140.jpg", "productName": "[\ud604\ub300 \ub2e8\ub3c5 \uc0c1\ud488] \ucc38\uc874 \uae30\ucd08 \ud2b8\ub9ac\ud50c \ud551\ud06c\ud551\ud06c \uc5d0\ub514\uc158", "customerPrice": "80,000\uc6d0", "productCategory": "\ubdf0\ud2f0", "marketPrice": 0, "benefitList": [], "productLink": "https://www.hyundaihmall.com/front/pda/itemPtc.do?slitmCd=2075792903"}, {"startTime": "16:40 ", "endTime": " 17:40", "productImage": "https://imagessl.hyundaihmall.com/static/3/6/18/79/2079186387_0_140.jpg", "productName": "BBC \ube44\ube44\uc548 \uc778\uacac \ucfe8\ucee4\ubc84 \ud504\ub9ac\ubb34\ube59 \ud328\ud0a4\uc9c0", "customerPrice": "134,910\uc6d0", "productCategory": "\uc774\ub108\ubca0\ub529", "marketPrice": "149,900\uc6d0", "benefitList": ["10%"], "productLink": "https://www.hyundaihmall.com/front/pda/itemPtc.do?slitmCd=2079186387"}, {"startTime": "17:40 ", "endTime": " 18:40", "productImage": "https://imagessl.hyundaihmall.com/static/5/4/45/72/2072454533_0_140.jpg", "productName": "\uba54\ub9ac\uce20 \uc62c\ubc14\ub978 \uc554\ubcf4\ud5d8", "customerPrice": "080-000-0000", "productCategory": "\uae08\uc735\uc0c1\ud488", "marketPrice": 0, "benefitList": [], "productLink": "https://www.hyundaihmall.com/front/pda/itemPtc.do?slitmCd=2072454533"}, {"startTime": "18:40 ", "endTime": " 19:40", "productImage": "https://imagessl.hyundaihmall.com/static/4/7/08/77/2077087499_0_140.jpg", "productName": "[BEAT ZET] \ube44\ud2b8\uc82f \uc2a4\ud300\ub2e4\ub9ac\ubbf8", "customerPrice": "133,000\uc6d0", "productCategory": "\ub9ac\ube59", "marketPrice": "138,000\uc6d0", "benefitList": ["4%"], "productLink": "https://www.hyundaihmall.com/front/pda/itemPtc.do?slitmCd=2077087499"}, {"startTime": "18:40 ", "endTime": " 19:40", "productImage": "https://imagessl.hyundaihmall.com/static/6/5/45/77/2077455621_0_140.jpg", "productName": "[BEAT ZET] \ube44\ud2b8\uc82f \uc2a4\ud300\ub2e4\ub9ac\ubbf8", "customerPrice": "133,000\uc6d0", "productCategory": "\ub9ac\ube59", "marketPrice": "138,000\uc6d0", "benefitList": ["4%"], "productLink": "https://www.hyundaihmall.com/front/pda/itemPtc.do?slitmCd=2077455621"}, {"startTime": "19:40 ", "endTime": " 20:45", "productImage": "https://imagessl.hyundaihmall.com/static/8/4/35/77/2077354873_0_140.JPG", "productName": "\ub178\uc640 \uc2a4\ud018\uc5b4 5.2L \ub300\uc6a9\ub7c9 \uc5d0\uc5b4\ud504\ub77c\uc774\uc5b4", "customerPrice": "99,000\uc6d0", "productCategory": "\uc8fc\ubc29", "marketPrice": "110,000\uc6d0", "benefitList": ["10%"], "productLink": "https://www.hyundaihmall.com/front/pda/itemPtc.do?slitmCd=2077354873"}, {"startTime": "19:40 ", "endTime": " 20:45", "productImage": "https://imagessl.hyundaihmall.com/static/5/9/81/77/2077819579_0_140.JPG", "productName": "\ub178\uc640 \uc2a4\ud018\uc5b4 5.2L \ub300\uc6a9\ub7c9 \uc5d0\uc5b4\ud504\ub77c\uc774\uc5b4", "customerPrice": "99,000\uc6d0", "productCategory": "\uc8fc\ubc29", "marketPrice": "110,000\uc6d0", "benefitList": ["10%"], "productLink": "https://www.hyundaihmall.com/front/pda/itemPtc.do?slitmCd=2077819579"}, {"startTime": "19:40 ", "endTime": " 20:45", "productImage": "https://imagessl.hyundaihmall.com/static/1/4/82/77/2077824136_0_140.jpg", "productName": "\ub178\uc640 \uc2a4\ud150 \uc5d0\uc5b4\ud504\ub77c\uc774\uc5b4 4L", "customerPrice": "79,800\uc6d0", "productCategory": "\uc8fc\ubc29", "marketPrice": "84,800\uc6d0", "benefitList": ["6%"], "productLink": "https://www.hyundaihmall.com/front/pda/itemPtc.do?slitmCd=2077824136"}, {"startTime": "20:45 ", "endTime": " 21:45", "productImage": "https://imagessl.hyundaihmall.com/static/2/4/53/73/2073534221_0_140.jpg", "productName": "(\ubb34)\ud765\uad6d\ud654\uc7ac \ucc29\ud55c\uac00\uaca9 \uac74\uac15\ubcf4\ud5d8", "customerPrice": "080-000-0000", "productCategory": "\uae08\uc735\uc0c1\ud488", "marketPrice": 0, "benefitList": [], "productLink": "https://www.hyundaihmall.com/front/pda/itemPtc.do?slitmCd=2073534221"}, {"startTime": "21:45 ", "endTime": " 22:45", "productImage": "https://imagessl.hyundaihmall.com/static/5/6/68/77/2077686507_0_140.jpg", "productName": "\ubc14\ub514\ud504\ub79c\ub4dc \uc548\ub9c8\uc758\uc790 \ub80c\ud0c8", "customerPrice": 0, "productCategory": "\ub80c\ud0c8", "marketPrice": 0, "benefitList": [], "productLink": "https://www.hyundaihmall.com/front/pda/itemPtc.do?slitmCd=2077686507"}, {"startTime": "22:45 ", "endTime": " 23:55", "productImage": "https://imagessl.hyundaihmall.com/static/8/6/13/79/2079136807_0_140.jpg", "productName": "\uc870\uc131\uc544 \uc288\ud37c\ud54f \ud30c\uc6cc \ud504\ub8e8\ud504 \ucee4\ubc84 \uc2a4\ud2f1\ud30c\uc6b4\ub370\uc774\uc158 \ub7f0\uce6d\ubc29\uc1a1 \ud328\ud0a4\uc9c0", "customerPrice": "71,100\uc6d0", "productCategory": "\ubdf0\ud2f0", "marketPrice": "79,000\uc6d0", "benefitList": ["10%"], "productLink": "https://www.hyundaihmall.com/front/pda/itemPtc.do?slitmCd=2079136807"}, {"startTime": "23:55 ", "endTime": " 01:00", "productImage": "https://imagessl.hyundaihmall.com/static/6/6/17/79/2079176688_0_140.jpg", "productName": "\uc0bc\uc131\ub178\ud2b8\ubd81 5 \uace0\uae09\ud329[NT550EBA-K28W] + JBL\uc2a4\ud53c\ucee4[JBLGO2ORG]", "customerPrice": "657,100\uc6d0", "productCategory": "\ub514\uc9c0\ud138\uac00\uc804", "marketPrice": "819,000\uc6d0", "benefitList": ["20%"], "productLink": "https://www.hyundaihmall.com/front/pda/itemPtc.do?slitmCd=2079176688"}, {"startTime": "23:55 ", "endTime": " 01:00", "productImage": "https://imagessl.hyundaihmall.com/static/5/8/17/79/2079178535_0_140.jpg", "productName": "\uc0bc\uc131\ub178\ud2b8\ubd81 5 \uace0\uae09\ud329[NT550EBA-K28B] + JBL\uc2a4\ud53c\ucee4[JBLGO2ORG]", "customerPrice": "657,100\uc6d0", "productCategory": "\ub514\uc9c0\ud138\uac00\uc804", "marketPrice": "819,000\uc6d0", "benefitList": ["20%"], "productLink": "https://www.hyundaihmall.com/front/pda/itemPtc.do?slitmCd=2079178535"}, {"startTime": "23:55 ", "endTime": " 01:00", "productImage": "https://imagessl.hyundaihmall.com/static/3/7/18/79/2079187387_0_140.jpg", "productName": "\uc0bc\uc131\ub178\ud2b8\ubd81 5 \uae30\ubcf8\ud329[NT550EBA-K24B] + JBL\uc2a4\ud53c\ucee4[JBLGO2ORG]", "customerPrice": "567,100\uc6d0", "productCategory": "\ub514\uc9c0\ud138\uac00\uc804", "marketPrice": "719,000\uc6d0", "benefitList": ["21%"], "productLink": "https://www.hyundaihmall.com/front/pda/itemPtc.do?slitmCd=2079187387"}, {"startTime": "23:55 ", "endTime": " 01:00", "productImage": "https://imagessl.hyundaihmall.com/static/6/4/93/78/2078934616_0_140.jpg", "productName": "\uc0bc\uc131\ub178\ud2b8\ubd81 9\uba54\ud0c8 \uace0\uae09\ud329 \uc544\uc774\uc5b8\uc2e4\ubc84[NT900X5J-K28]+[\uc0ac\uc740\ud488:\uc0bc\uc131 \ub808\uc774\uc838 \ud504\ub9b0\ud2b8 \ub4f1 6\uc885]", "customerPrice": "1,114,100\uc6d0", "productCategory": "\ub514\uc9c0\ud138\uac00\uc804", "marketPrice": "1,349,000\uc6d0", "benefitList": ["17%"], "productLink": "https://www.hyundaihmall.com/front/pda/itemPtc.do?slitmCd=2078934616"}, {"startTime": "23:55 ", "endTime": " 01:00", "productImage": "https://imagessl.hyundaihmall.com/static/8/4/93/78/2078934852_0_140.jpg", "productName": "\uc0bc\uc131\ub178\ud2b8\ubd81 9\uba54\ud0c8 \uace0\uae09\ud329 \ubbf8\ub124\ub784\ud654\uc774\ud2b8[NT900X5J-K28W]+[\uc0ac\uc740\ud488:\uc0bc\uc131 \ub808\uc774\uc838 \ud504\ub9b0\ud130 \ub4f1 6\uc885 ]", "customerPrice": "1,114,100\uc6d0", "productCategory": "\ub514\uc9c0\ud138\uac00\uc804", "marketPrice": "1,349,000\uc6d0", "benefitList": ["17%"], "productLink": "https://www.hyundaihmall.com/front/pda/itemPtc.do?slitmCd=2078934852"}, {"startTime": "23:55 ", "endTime": " 01:00", "productImage": "https://imagessl.hyundaihmall.com/static/4/5/93/78/2078935451_0_140.jpg", "productName": "\uc0bc\uc131\ub178\ud2b8\ubd81 9\uba54\ud0c8 \uae30\ubcf8\ud329 \uc544\uc774\uc5b8\uc2e4\ubc84[NT900X5J-K14]+[\uc0ac\uc740\ud488:\uc0bc\uc131 \ub808\uc774\uc838 \ud504\ub9b0\ud130 \ub4f1 6\uc885 ]", "customerPrice": "880,100\uc6d0", "productCategory": "\ub514\uc9c0\ud138\uac00\uc804", "marketPrice": "1,089,000\uc6d0", "benefitList": ["19%"], "productLink": "https://www.hyundaihmall.com/front/pda/itemPtc.do?slitmCd=2078935451"}, {"startTime": "23:55 ", "endTime": " 01:00", "productImage": "https://imagessl.hyundaihmall.com/static/7/2/95/78/2078952781_0_140.jpg", "productName": "\uc0bc\uc131\ub178\ud2b8\ubd81 PEN[NT930QBE-K38W]+[\uc0ac\uc740\ud488:\ub808\uc774\uc838 \ud504\ub9b0\ud130]", "customerPrice": "1,292,810\uc6d0", "productCategory": "\ub514\uc9c0\ud138\uac00\uc804", "marketPrice": "1,799,000\uc6d0", "benefitList": ["28%"], "productLink": "https://www.hyundaihmall.com/front/pda/itemPtc.do?slitmCd=2078952781"}, {"startTime": "23:55 ", "endTime": " 01:00", "productImage": "https://imagessl.hyundaihmall.com/static/8/2/95/78/2078952864_0_140.jpg", "productName": "\uc0bc\uc131\ub178\ud2b8\ubd81 PEN[NT930QBE-K38]+[\uc0ac\uc740\ud488:\ub808\uc774\uc838\ud504\ub9b0\ud130]", "customerPrice": "1,469,100\uc6d0", "productCategory": "\ub514\uc9c0\ud138\uac00\uc804", "marketPrice": "1,799,000\uc6d0", "benefitList": ["18%"], "productLink": "https://www.hyundaihmall.com/front/pda/itemPtc.do?slitmCd=2078952864"}, {"startTime": "23:55 ", "endTime": " 01:00", "productImage": "https://imagessl.hyundaihmall.com/static/9/2/95/78/2078952965_0_140.jpg", "productName": "\uc0bc\uc131\ub178\ud2b8\ubd81 PEN[NT930QBE-K28]+[\uc0ac\uc740\ud488:\ub808\uc774\uc838\ud504\ub9b0\ud130]", "customerPrice": "1,334,100\uc6d0", "productCategory": "\ub514\uc9c0\ud138\uac00\uc804", "marketPrice": "1,649,000\uc6d0", "benefitList": ["19%"], "productLink": "https://www.hyundaihmall.com/front/pda/itemPtc.do?slitmCd=2078952965"}, {"startTime": "23:55 ", "endTime": " 01:00", "productImage": "https://imagessl.hyundaihmall.com/static/3/3/07/79/2079073379_0_140.jpg", "productName": "\uc0bc\uc131\ub178\ud2b8\ubd81 Pen S[NT950SBE-K58W]+[\uc0ac\uc740\ud488:\ub808\uc774\uc838 \ud504\ub9b0\ud130+\uba40\ud2f0\ud3ec\ud2b8\uc5b4\ub311\ud130]", "customerPrice": "1,780,100\uc6d0", "productCategory": "\ub514\uc9c0\ud138\uac00\uc804", "marketPrice": "2,189,000\uc6d0", "benefitList": ["19%"], "productLink": "https://www.hyundaihmall.com/front/pda/itemPtc.do?slitmCd=2079073379"}, {"startTime": "23:55 ", "endTime": " 01:00", "productImage": "https://imagessl.hyundaihmall.com/static/2/4/07/79/2079074273_0_140.jpg", "productName": "\uc0bc\uc131\ub178\ud2b8\ubd81 Pen S[NT950SBE-K38]+[\uc0ac\uc740\ud488:\ub808\uc774\uc838 \ud504\ub9b0\ud130+\uba40\ud2f0\ud3ec\ud2b8\uc5b4\ub311\ud130]", "customerPrice": "1,600,100\uc6d0", "productCategory": "\ub514\uc9c0\ud138\uac00\uc804", "marketPrice": "1,989,000\uc6d0", "benefitList": ["20%"], "productLink": "https://www.hyundaihmall.com/front/pda/itemPtc.do?slitmCd=2079074273"}, {"startTime": "23:55 ", "endTime": " 01:00", "productImage": "https://imagessl.hyundaihmall.com/static/7/0/19/79/2079190737_0_140.jpg", "productName": "\uc0bc\uc131 \ub178\ud2b8\ubd81 FLASH \ub9b0\ub128\ud654\uc774\ud2b8[NT530XBB-K14W]", "customerPrice": "639,000\uc6d0", "productCategory": "\ub514\uc9c0\ud138\uac00\uc804", "marketPrice": "709,000\uc6d0", "benefitList": ["10%"], "productLink": "https://www.hyundaihmall.com/front/pda/itemPtc.do?slitmCd=2079190737"}, {"startTime": "23:55 ", "endTime": " 01:00", "productImage": "https://imagessl.hyundaihmall.com/static/3/2/19/79/2079192373_0_140.jpg", "productName": "\uc0bc\uc131 \ub178\ud2b8\ubd81 FLASH \uc18c\ud504\ud2b8\ucf54\ub784[NT530XBB-K14C]", "customerPrice": "575,100\uc6d0", "productCategory": "\ub514\uc9c0\ud138\uac00\uc804", "marketPrice": "709,000\uc6d0", "benefitList": ["19%"], "productLink": "https://www.hyundaihmall.com/front/pda/itemPtc.do?slitmCd=2079192373"}, {"startTime": "23:55 ", "endTime": " 01:00", "productImage": "https://imagessl.hyundaihmall.com/static/5/2/19/79/2079192556_0_140.jpg", "productName": "\uc0bc\uc131 \ub178\ud2b8\ubd81 FLASH \ud2b8\uc70c\ucc28\ucf5c[NT530XBB-K14B]", "customerPrice": "599,000\uc6d0", "productCategory": "\ub514\uc9c0\ud138\uac00\uc804", "marketPrice": "669,000\uc6d0", "benefitList": ["10%"], "productLink": "https://www.hyundaihmall.com/front/pda/itemPtc.do?slitmCd=2079192556"}, {"startTime": "23:55 ", "endTime": " 01:00", "productImage": "https://imagessl.hyundaihmall.com/static/2/5/33/79/2079335251_0_140.jpg", "productName": "\uc0bc\uc131\ub178\ud2b8\ubd81 5 \uace0\uae09\ud329[NT550EBA-K28B]", "customerPrice": "699,000\uc6d0", "productCategory": "\ub514\uc9c0\ud138\uac00\uc804", "marketPrice": "779,000\uc6d0", "benefitList": ["10%"], "productLink": "https://www.hyundaihmall.com/front/pda/itemPtc.do?slitmCd=2079335251"}, {"startTime": "23:55 ", "endTime": " 01:00", "productImage": "https://imagessl.hyundaihmall.com/static/3/5/33/79/2079335341_0_140.jpg", "productName": "\uc0bc\uc131\ub178\ud2b8\ubd81 5 \uae30\ubcf8\ud329[NT550EBA-K24B]", "customerPrice": "599,000\uc6d0", "productCategory": "\ub514\uc9c0\ud138\uac00\uc804", "marketPrice": "679,000\uc6d0", "benefitList": ["12%"], "productLink": "https://www.hyundaihmall.com/front/pda/itemPtc.do?slitmCd=2079335341"}]