[{"startTime": "\uc624\uc804 2:00 ", "endTime": " \uc624\uc804 3:20", "productImage": "http://image.nsmall.com/itemimg/4/27/784/27842784_G.jpg", "productName": "[\ud37c\uc2a4\ud2b8] [TV]\ub354\ud37c\uc2a4\ud2b8 \uc720\uae30\ub18d \ub178\ub2c8 \ucd1d 4\ubc15\uc2a4", "customerPrice": "197,000\uc6d0", "productCategory": "", "productLink": "http://www.nsmall.com/ProductDisplay?menuUri=NSItemDetailView&partNumber='27842784'", "marketPrice": "198,000\uc6d0", "benefitList": [""]}, {"startTime": "\uc624\uc804 2:00 ", "endTime": " \uc624\uc804 3:20", "productImage": "http://image.nsmall.com/itemimg/0/27/880/27828880_G.jpg", "productName": "[\uc548\ub3d9\uac04\uace0\ub4f1\uc5b4] [TV]\uc21c\uc0b4\uc548\ub3d9\uac04\uace0\ub4f1\uc5b4 100gX28\ud329", "customerPrice": "29,900\uc6d0", "productCategory": "", "productLink": "http://www.nsmall.com/ProductDisplay?menuUri=NSItemDetailView&partNumber='27828880'", "marketPrice": "30,900\uc6d0", "benefitList": [""]}, {"startTime": "\uc624\uc804 2:00 ", "endTime": " \uc624\uc804 3:20", "productImage": "http://image.nsmall.com/itemimg/7/28/697/28119697_G.jpg", "productName": "[\uac70\ubb38\ub3c4\ud574\ud48d\uc465] [TV]\uac70\ubb38\ub3c4 \ud574\ud48d\uc465\uc1a1\ud3b8\uc138\ud2b8(\uc465\uac1c\ub5a1 12\ubd09+\uc465\uc1a1\ud3b8 2\ubd09+\ub0c9\ub3d9\uc465 3\ubd09)", "customerPrice": "38,900\uc6d0", "productCategory": "", "productLink": "http://www.nsmall.com/ProductDisplay?menuUri=NSItemDetailView&partNumber='28119697'", "marketPrice": "39,900\uc6d0", "benefitList": [""]}, {"startTime": "\uc624\uc804 2:00 ", "endTime": " \uc624\uc804 3:20", "productImage": "http://image.nsmall.com/itemimg/9/28/699/28119699_G.jpg", "productName": "[\uac70\ubb38\ub3c4\ud574\ud48d\uc465] [TV]\uac70\ubb38\ub3c4 \ud574\ud48d\uc465\uc1a1\ud3b8+\uc465\ubd84\ub9d0\uc138\ud2b8(\uc465\uac1c\ub5a1 12\ubd09+\uc465\uc1a1\ud3b8 2\ubd09+\ub0c9\ub3d9\uc465 3\ubd09+\ud574\ud48d\uc465\ubd84\ub9d0 100g)", "customerPrice": "48,900\uc6d0", "productCategory": "", "productLink": "http://www.nsmall.com/ProductDisplay?menuUri=NSItemDetailView&partNumber='28119699'", "marketPrice": "49,900\uc6d0", "benefitList": [""]}, {"startTime": "\uc624\uc804 2:00 ", "endTime": " \uc624\uc804 3:20", "productImage": "http://image.nsmall.com/itemimg/1/27/501/27939501_G.jpg", "productName": "[\uc560\ud50c\ud2b8\ub9ac \uae40\uc57d\uc0ac\ub124] [TV]\ubca8\uae30\uc5d0 \uc720\uc0b0\uade0 \ub2e4\uc774\uc5b4\ud2b8 \ud2b8\ub9ac\ud50c\ub7ec\uc2a4 12\ubc15\uc2a4/ 24\uc8fc\ubd84", "customerPrice": "177,000\uc6d0", "productCategory": "", "productLink": "http://www.nsmall.com/ProductDisplay?menuUri=NSItemDetailView&partNumber='27939501'", "marketPrice": "178,000\uc6d0", "benefitList": [""]}, {"startTime": "\uc624\uc804 2:00 ", "endTime": " \uc624\uc804 3:20", "productImage": "http://image.nsmall.com/itemimg/5/27/535/27472535_G.jpg", "productName": "[\uc560\ud50c\ud2b8\ub9ac \uae40\uc57d\uc0ac\ub124] [TV]\ubca8\uae30\uc5d0 \uc720\uc0b0\uade0 \ub2e4\uc774\uc5b4\ud2b8 \ud2b8\ub9ac\ud50c\ub7ec\uc2a4 6\ubc15\uc2a4/12\uc8fc\ubd84", "customerPrice": "98,000\uc6d0", "productCategory": "", "productLink": "http://www.nsmall.com/ProductDisplay?menuUri=NSItemDetailView&partNumber='27472535'", "marketPrice": "99,000\uc6d0", "benefitList": [""]}, {"startTime": "\uc624\uc804 4:00 ", "endTime": " \uc624\uc804 6:00", "productImage": "http://image.nsmall.com/itemimg/0/27/280/27940280_G.jpg", "productName": "[TV]\ud608\uad00\ud314\ud314 \ud53c\ubd80\ud314\ud314 12\ubc15\uc2a4/\ucd1d 6\uac1c\uc6d4\ubd84", "customerPrice": "316,000\uc6d0", "productCategory": "", "productLink": "", "marketPrice": 0, "benefitList": [""]}, {"startTime": "\uc624\uc804 4:00 ", "endTime": " \uc624\uc804 6:00", "productImage": "http://image.nsmall.com/itemimg/3/27/583/27774583_G.jpg", "productName": "[TV](\ubb34\uc774\uc790)\ud608\uad00\ud314\ud314 \ud53c\ubd80\ud314\ud314 6\ubc15\uc2a4/\ucd1d 3\uac1c\uc6d4\ubd84", "customerPrice": "168,000\uc6d0", "productCategory": "", "productLink": "", "marketPrice": "178,000\uc6d0", "benefitList": [""]}, {"startTime": "\uc624\uc804 4:00 ", "endTime": " \uc624\uc804 6:00", "productImage": "http://image.nsmall.com/itemimg/2/27/302/27238302_G.jpg", "productName": "[\ud55c\ubbf8\ud5ec\uc2a4\ucf00\uc5b4] [TV]\ud55c\ubbf8 \uace0\uce7c\uc298 \ube0c\ub77c\uc9c8\ub108\ud2b8\uc640 \uc0ac\ucc28\uc778\uce58 \uc804\ub450\uc720 96\ud329", "customerPrice": "39,510\uc6d0", "productCategory": "", "productLink": "http://www.nsmall.com/ProductDisplay?menuUri=NSItemDetailView&partNumber='27238302'", "marketPrice": "43,900\uc6d0", "benefitList": [""]}, {"startTime": "\uc624\uc804 4:00 ", "endTime": " \uc624\uc804 6:00", "productImage": "http://image.nsmall.com/itemimg/8/27/968/27881968_G.jpg", "productName": "[\uc774\uacbd\uc81c] [TV](\uc77c\uc2dc\ubd88)\ud669\uae08\uad00\uc808 4\uac1c\uc6d4\ubd84", "customerPrice": "158,000\uc6d0", "productCategory": "", "productLink": "", "marketPrice": 0, "benefitList": [""]}, {"startTime": "\uc624\uc804 4:00 ", "endTime": " \uc624\uc804 6:00", "productImage": "http://image.nsmall.com/itemimg/5/27/345/27872345_G.jpg", "productName": "[\uc774\uacbd\uc81c] [TV](\ubb34\uc774\uc790)\ud669\uae08\uad00\uc808 4\uac1c\uc6d4\ubd84", "customerPrice": "178,000\uc6d0", "productCategory": "", "productLink": "", "marketPrice": 0, "benefitList": [""]}, {"startTime": "\uc624\uc804 4:00 ", "endTime": " \uc624\uc804 6:00", "productImage": "http://image.nsmall.com/itemimg/2/27/902/27923902_G.jpg", "productName": "[\uc774\uacbd\uc81c] [TV]\ud669\uae08\uad00\uc808 2\uac1c\uc6d4\ubd84", "customerPrice": "108,000\uc6d0", "productCategory": "", "productLink": "", "marketPrice": "109,000\uc6d0", "benefitList": [""]}, {"startTime": "\uc624\uc804 4:00 ", "endTime": " \uc624\uc804 6:00", "productImage": "http://image.nsmall.com/itemimg/0/27/650/27474650_G.jpg", "productName": "[TV](\uc77c\uc2dc\ubd88)\ub2e5\ud130\uc288\ud37c\uce78 12\ubc15\uc2a4/12\uac1c\uc6d4\ubd84", "customerPrice": "149,430\uc6d0", "productCategory": "", "productLink": "http://www.nsmall.com/ProductDisplay?menuUri=NSItemDetailView&partNumber='27474650'", "marketPrice": "158,300\uc6d0", "benefitList": ["[\ubbf8\ub9ac\uc8fc\ubb38 5% \ud560\uc778]"]}, {"startTime": "\uc624\uc804 4:00 ", "endTime": " \uc624\uc804 6:00", "productImage": "http://image.nsmall.com/itemimg/3/27/613/27474613_G.jpg", "productName": "[TV](\ubb34\uc774\uc790)\ub2e5\ud130\uc288\ud37c\uce78 12\ubc15\uc2a4/12\uac1c\uc6d4\ubd84", "customerPrice": "158,930\uc6d0", "productCategory": "", "productLink": "http://www.nsmall.com/ProductDisplay?menuUri=NSItemDetailView&partNumber='27474613'", "marketPrice": "168,300\uc6d0", "benefitList": ["[\ubbf8\ub9ac\uc8fc\ubb38 5% \ud560\uc778]"]}, {"startTime": "\uc624\uc804 4:00 ", "endTime": " \uc624\uc804 6:00", "productImage": "http://image.nsmall.com/itemimg/2/28/902/28171902_G.jpg", "productName": "[TV]\ub18d\ud611 \uc218\ud638\ucc9c\uc0ac \ud585\uc300 10kg+10kg", "customerPrice": "53,900\uc6d0", "productCategory": "", "productLink": "http://www.nsmall.com/ProductDisplay?menuUri=NSItemDetailView&partNumber='28171902'", "marketPrice": "54,900\uc6d0", "benefitList": [""]}, {"startTime": "\uc624\uc804 4:00 ", "endTime": " \uc624\uc804 6:00", "productImage": "http://image.nsmall.com/itemimg/9/27/209/27802209_G.jpg", "productName": "[\ub300\uc11c\uc591] [TV]\ub300\uc11c\uc591 \uc190\uc9c8\uac08\uce58 200gX13\ud329", "customerPrice": "37,900\uc6d0", "productCategory": "", "productLink": "http://www.nsmall.com/ProductDisplay?menuUri=NSItemDetailView&partNumber='27802209'", "marketPrice": "39,900\uc6d0", "benefitList": ["[\ubbf8\ub9ac\uc8fc\ubb38 5% \ud560\uc778]"]}, {"startTime": "\uc624\uc804 9:25 ", "endTime": " \uc624\uc804 10:25", "productImage": "http://image.nsmall.com/itemimg/3/28/293/28245293_G.jpg", "productName": "[\uc218\ub824\ud55c] [TV]\uc218\ub824\ud55c \uace8\ub4e0\ub3d9\uc548\ucfe0\uc158(\ubcf8\ud488 2\uc885+\ub9ac\ud544 4\uc885+\uc5d0\uc13c\uc2a4X2+\ud30c\uc6b0\uce58X2)", "customerPrice": "83,600\uc6d0", "productCategory": "", "productLink": "http://www.nsmall.com/ProductDisplay?menuUri=NSItemDetailView&partNumber='28245293'", "marketPrice": "89,000\uc6d0", "benefitList": ["[\ubbf8\ub9ac\uc8fc\ubb38 5% \ud560\uc778]"]}, {"startTime": "\uc624\uc804 9:25 ", "endTime": " \uc624\uc804 10:25", "productImage": "http://image.nsmall.com/itemimg/8/27/318/27398318_G.jpg", "productName": "[\uc218\ub824\ud55c] [eTV]\uc218\ub824\ud55c \ud56d\ub178\ud654\uc570\ud50c 4\ubcd1+\uc2a4\ud0a8+\uc5d0\uba40\uc804+\ud06c\ub9bc", "customerPrice": "64,600\uc6d0", "productCategory": "", "productLink": "http://www.nsmall.com/ProductDisplay?menuUri=NSItemDetailView&partNumber='27398318'", "marketPrice": "69,000\uc6d0", "benefitList": ["[\ubbf8\ub9ac\uc8fc\ubb38 5% \ud560\uc778]"]}, {"startTime": "\uc624\uc804 9:25 ", "endTime": " \uc624\uc804 10:25", "productImage": "http://image.nsmall.com/itemimg/7/28/737/28220737_G.jpg", "productName": "[\uc218\ub824\ud55c] [eTV]\uc218\ub824\ud55c \ud6a8\uc724 \uc5d0\uc13c\uc2a4+\ud06c\ub9bc+\uc218\ubd84\uc824\ud06c\ub9bc", "customerPrice": "51,300\uc6d0", "productCategory": "", "productLink": "http://www.nsmall.com/ProductDisplay?menuUri=NSItemDetailView&partNumber='28220737'", "marketPrice": "55,000\uc6d0", "benefitList": ["[\ubbf8\ub9ac\uc8fc\ubb38 5% \ud560\uc778]"]}, {"startTime": "\uc624\ud6c4 3:35 ", "endTime": " \uc624\ud6c4 4:30", "productImage": "http://image.nsmall.com/itemimg/2/28/662/28250662_G.jpg", "productName": "[\ub9ac\ub098\ube14\ub8e8] \ub9ac\ub098\ube14\ub8e8 19SS \ub9b0\ub128 \ube14\ub80c\ub514\ub4dc \uc218\ud2b8", "customerPrice": "48,000\uc6d0", "productCategory": "", "productLink": "", "marketPrice": "49,000\uc6d0", "benefitList": [""]}, {"startTime": "\uc624\ud6c4 4:30 ", "endTime": " \uc624\ud6c4 5:10", "productImage": "http://image.nsmall.com/itemimg/6/27/246/27666246_G.jpg", "productName": "[LA\uac08\ube44:\uc804\ucca0\uc6b0] [TV]\uc804\ucca0\uc6b0 LA\uac08\ube44 500gX8\ud329", "customerPrice": "71,150\uc6d0", "productCategory": "", "productLink": "http://www.nsmall.com/ProductDisplay?menuUri=NSItemDetailView&partNumber='27666246'", "marketPrice": "75,900\uc6d0", "benefitList": ["[\ubbf8\ub9ac\uc8fc\ubb38 5% \ud560\uc778]"]}, {"startTime": "\uc624\ud6c4 5:10 ", "endTime": " \uc624\ud6c4 5:50", "productImage": "http://image.nsmall.com/itemimg/2/28/262/28207262_G.jpg", "productName": "[\uc804\ucca0\uc6b0 \uc74c\uc2dd\uc0ac\ub791] [TV]\uc804\ucca0\uc6b0 \uace0\ud5a5\ub0c9\uba74 25\uc778\ubd84(\uc721\uc218 15\ud329+\ube44\ube54\uc7a5 10\ud329)", "customerPrice": "37,900\uc6d0", "productCategory": "", "productLink": "http://www.nsmall.com/ProductDisplay?menuUri=NSItemDetailView&partNumber='28207262'", "marketPrice": "40,900\uc6d0", "benefitList": ["[\ubbf8\ub9ac\uc8fc\ubb38 5% \ud560\uc778]"]}, {"startTime": "\uc624\ud6c4 5:50 ", "endTime": " \uc624\ud6c4 6:35", "productImage": "http://image.nsmall.com/itemimg/9/28/889/28077889_G.jpg", "productName": "[\uace0\uba54] [TV]\uace0\uba54 \ud568\ubc15\uc2a4\ud14c\uc774\ud06c \uc138\ud2b8(\ud568\ubc15\uc2a4\ud14c\uc774\ud06cX10\ubd09+\uce58\uc988\ud568\ubc15\uc2a4\ud14c\uc774\ud06cX10\ubd09)", "customerPrice": "37,900\uc6d0", "productCategory": "", "productLink": "http://www.nsmall.com/ProductDisplay?menuUri=NSItemDetailView&partNumber='28077889'", "marketPrice": "40,900\uc6d0", "benefitList": ["[\ubbf8\ub9ac\uc8fc\ubb38 5% \ud560\uc778]"]}, {"startTime": "\uc624\ud6c4 5:50 ", "endTime": " \uc624\ud6c4 6:35", "productImage": "http://image.nsmall.com/itemimg/2/28/132/28062132_G.jpg", "productName": "[\uace0\uba54] [eTV]CJ \uace0\uba54 \ud06c\ub9ac\uc2a4\ud53c\ud56b\ub3c4\uadf8\uc138\ud2b8(\ud06c\ub9ac\uc2a4\ud53c\ud56b\ub3c4\uadf8X3\ubd09+\uce58\uc988\ud06c\ub9ac\uc2a4\ud53c\ud56b\ub3c4\uadf8X3\ubd09)", "customerPrice": "39,800\uc6d0", "productCategory": "", "productLink": "http://www.nsmall.com/ProductDisplay?menuUri=NSItemDetailView&partNumber='28062132'", "marketPrice": "41,900\uc6d0", "benefitList": ["[\ubbf8\ub9ac\uc8fc\ubb38 5% \ud560\uc778]"]}, {"startTime": "\uc624\ud6c4 5:50 ", "endTime": " \uc624\ud6c4 6:35", "productImage": "http://image.nsmall.com/itemimg/9/28/029/28081029_G.jpg", "productName": "[\uace0\uba54] [eTV]CJ \uace0\uba54 \uadf8\ub9b4\ud53c\uc790 2\uc885(\uadf8\ub9b4\ud53c\uc790\ubd88\uace0\uae30X3+\uadf8\ub9b4\ud53c\uc790\ud3ec\ud14c\uc774\ud1a0X3)", "customerPrice": "34,100\uc6d0", "productCategory": "", "productLink": "http://www.nsmall.com/ProductDisplay?menuUri=NSItemDetailView&partNumber='28081029'", "marketPrice": "35,900\uc6d0", "benefitList": ["[\ubbf8\ub9ac\uc8fc\ubb38 5% \ud560\uc778]"]}, {"startTime": "\uc624\ud6c4 5:50 ", "endTime": " \uc624\ud6c4 6:35", "productImage": "http://image.nsmall.com/itemimg/2/28/272/28081272_G.jpg", "productName": "[\uace0\uba54] [eTV]CJ \uace0\uba54 \ud06c\ub9ac\uc2a4\ud53c\uce58\ud0a8X2\ubd09+\ub108\uac9fX3\ubd09", "customerPrice": "33,150\uc6d0", "productCategory": "", "productLink": "http://www.nsmall.com/ProductDisplay?menuUri=NSItemDetailView&partNumber='28081272'", "marketPrice": "34,900\uc6d0", "benefitList": ["[\ubbf8\ub9ac\uc8fc\ubb38 5% \ud560\uc778]"]}, {"startTime": "\uc624\ud6c4 6:35 ", "endTime": " \uc624\ud6c4 7:40", "productImage": "http://image.nsmall.com/itemimg/4/28/114/28043114_G.jpg", "productName": "[\uce90\ub9ac\uc5b4] [TV]\uce90\ub9ac\uc5b4 \uc5d0\uc5b4\ucee8 AMC18VX3SAGH 18\ud615+6\ud615", "customerPrice": "1,899,000\uc6d0", "productCategory": "", "productLink": "http://www.nsmall.com/ProductDisplay?menuUri=NSItemDetailView&partNumber='28043114'", "marketPrice": "2,049,000\uc6d0", "benefitList": [""]}, {"startTime": "\uc624\ud6c4 6:35 ", "endTime": " \uc624\ud6c4 7:40", "productImage": "http://image.nsmall.com/itemimg/5/28/115/28043115_G.jpg", "productName": "[\uce90\ub9ac\uc5b4] [TV]\uce90\ub9ac\uc5b4 \uc5d0\uc5b4\ucee8 AMC18VX3SA 18\ud615", "customerPrice": "1,649,000\uc6d0", "productCategory": "", "productLink": "http://www.nsmall.com/ProductDisplay?menuUri=NSItemDetailView&partNumber='28043115'", "marketPrice": "1,799,000\uc6d0", "benefitList": [""]}, {"startTime": "\uc624\ud6c4 6:35 ", "endTime": " \uc624\ud6c4 7:40", "productImage": "http://image.nsmall.com/itemimg/6/28/116/28043116_G.jpg", "productName": "[\uce90\ub9ac\uc5b4] [TV]\uce90\ub9ac\uc5b4 \uc5d0\uc5b4\ucee8 AMC16VX3SAGH 16\ud615+6\ud615", "customerPrice": "1,749,000\uc6d0", "productCategory": "", "productLink": "http://www.nsmall.com/ProductDisplay?menuUri=NSItemDetailView&partNumber='28043116'", "marketPrice": "1,899,000\uc6d0", "benefitList": [""]}, {"startTime": "\uc624\ud6c4 6:35 ", "endTime": " \uc624\ud6c4 7:40", "productImage": "http://image.nsmall.com/itemimg/7/28/117/28043117_G.jpg", "productName": "[\uce90\ub9ac\uc5b4] [TV]\uce90\ub9ac\uc5b4 \uc5d0\uc5b4\ucee8 AMC16VX3SA 16\ud615", "customerPrice": "1,499,000\uc6d0", "productCategory": "", "productLink": "http://www.nsmall.com/ProductDisplay?menuUri=NSItemDetailView&partNumber='28043117'", "marketPrice": "1,629,000\uc6d0", "benefitList": [""]}, {"startTime": "\uc624\ud6c4 8:40 ", "endTime": " \uc624\ud6c4 9:40", "productImage": "http://image.nsmall.com/itemimg/7/28/077/28225077_G.jpg", "productName": "[\uc774\ub86c \ud669\uc131\uc8fc \uc0dd\uc2dd] [TV]\ud669\uc131\uc8fc\uc0dd\uc2dd\uc2a4\ud398\uc15c 4\ubc15\uc2a4+\uc804\ub3d9\uc250\uc774\ucee4+\uc774\ub86c \ud669\uc131\uc8fc \ubc1c\uc544\uc57d\ucf69 \ub450\uc720 2\ubc15\uc2a4", "customerPrice": "197,000\uc6d0", "productCategory": "", "productLink": "http://www.nsmall.com/ProductDisplay?menuUri=NSItemDetailView&partNumber='28225077'", "marketPrice": "198,000\uc6d0", "benefitList": [""]}, {"startTime": "\uc624\ud6c4 9:40 ", "endTime": " \uc624\ud6c4 10:45", "productImage": "http://image.nsmall.com/itemimg/8/28/148/28236148_G.jpg", "productName": "[\uc528\ucf54\uc804\uc790] (2019\ub144 \uc2e0\uc0c1\ud488)PN \ud48d\ub144 \uc778\ub355\uc158 \ub80c\ud0c8", "customerPrice": 0, "productCategory": "", "productLink": "http://www.nsmall.com/ProductDisplay?menuUri=NSItemDetailView&partNumber='28236148'", "marketPrice": 0, "benefitList": [""]}, {"startTime": "\uc624\ud6c4 11:55 ", "endTime": " \uc624\uc804 1:00", "productImage": "http://image.nsmall.com/itemimg/6/28/416/28249416_G.jpg", "productName": "[\ub9ac\ub9ac\ucf54\uc2a4] [10% \uc989\uc2dc\ud560\uc778]\ub9ac\ub9ac\ucf54\uc2a4 \uc5d0\uc774\uc9c0\uc624\ubc84(\uc2a4\ud0a8X2+\uc5d0\uba40\uc804X2+\uc911\uc6a9\ub7c9(\uc2a4\ud0a8+\uc5d0\uba40\uc804)X2+\ud06c\ub9bcX5+\uc138\ub7fc+(\uc0c1\ud488\ud3c9\uc2dc)\uc138\ub7fc)", "customerPrice": "125,100\uc6d0", "productCategory": "", "productLink": "http://www.nsmall.com/ProductDisplay?menuUri=NSItemDetailView&partNumber='28249416'", "marketPrice": "140,000\uc6d0", "benefitList": ["[\ubbf8\ub9ac\uc8fc\ubb38 5% \ud560\uc778]"]}]